xdt.py
xdtclassifier-1.0.1.dist-info/LICENSE
xdtclassifier-1.0.1.dist-info/METADATA
xdtclassifier-1.0.1.dist-info/WHEEL
xdtclassifier-1.0.1.dist-info/top_level.txt
xdtclassifier-1.0.1.dist-info/RECORD
