Metadata-Version: 2.1
Name: xdtclassifier
Version: 1.0.1
Summary: XDT (Exact Decision Tree) - High-performance decision tree classifier with exact split optimization
Home-page: https://github.com/nqmn/xdt
Author: mohdadil
Author-email: mohdadil@live.com
Maintainer: mohdadil
License: MIT License
Project-URL: Homepage, https://github.com/nqmn/xdt
Project-URL: Repository, https://github.com/nqmn/xdt
Project-URL: Documentation, https://github.com/nqmn/xdt#readme
Project-URL: Bug Reports, https://github.com/nqmn/xdt/issues
Keywords: machine-learning,decision-tree,classification,xdt,exact-splits,histogram,optimization
Classifier: Development Status :: 4 - Beta
Classifier: Intended Audience :: Developers
Classifier: Intended Audience :: Science/Research
Classifier: License :: OSI Approved :: MIT License
Classifier: Operating System :: OS Independent
Classifier: Programming Language :: Python :: 3
Classifier: Programming Language :: Python :: 3.8
Classifier: Programming Language :: Python :: 3.9
Classifier: Programming Language :: Python :: 3.10
Classifier: Programming Language :: Python :: 3.11
Classifier: Programming Language :: Python :: 3.12
Classifier: Topic :: Scientific/Engineering :: Artificial Intelligence
Classifier: Topic :: Scientific/Engineering :: Information Analysis
Classifier: Topic :: Software Development :: Libraries :: Python Modules
Requires-Python: >=3.8
License-File: LICENSE
Requires-Dist: numpy>=1.19.0
Requires-Dist: pandas>=1.3.0
Requires-Dist: numba>=0.56.0
Requires-Dist: psutil>=5.8.0
Requires-Dist: scikit-learn>=1.0.0
Provides-Extra: benchmark
Requires-Dist: matplotlib>=3.3.0; extra == "benchmark"
Requires-Dist: seaborn>=0.11.0; extra == "benchmark"
Provides-Extra: dev
Requires-Dist: pytest>=6.0; extra == "dev"
Requires-Dist: pytest-cov; extra == "dev"
Requires-Dist: black; extra == "dev"
Requires-Dist: flake8; extra == "dev"
Requires-Dist: mypy; extra == "dev"
